enamllexer/__init__.py
enamllexer/lexer.py
pygments_enaml/__init__.py
pygments_enaml/lexer.py
pygments_enaml-0.1.0.dist-info/METADATA
pygments_enaml-0.1.0.dist-info/RECORD
pygments_enaml-0.1.0.dist-info/WHEEL
pygments_enaml-0.1.0.dist-info/entry_points.txt
pygments_enaml-0.1.0.dist-info/top_level.txt
